Metadata-Version: 1.1
Name: custom-text-test-runner
Version: 0.1.1
Summary: Python Custom Text Test Runner
Home-page: https://github.com/agramian/custom-text-test-runner
Author: Abtin Gramian
Author-email: abtin.gramian@gmail.com
License: UNKNOWN
Download-URL: https://github.com/agramian/custom-text-test-runner/tarball/v0.1.1
Keywords: unittest,custom,test,runner,result,json
Platform: UNKNOWN
